workrave_break_info.py
workrave_break_info-0.1.1.dist-info/licenses/LICENSE
workrave_break_info-0.1.1.dist-info/METADATA
workrave_break_info-0.1.1.dist-info/WHEEL
workrave_break_info-0.1.1.dist-info/entry_points.txt
workrave_break_info-0.1.1.dist-info/top_level.txt
workrave_break_info-0.1.1.dist-info/RECORD
