Metadata-Version: 2.4
Name: workrave_break_info
Version: 0.1.1
Summary: Allows info from Workrave timers to appear in tools like Waybar, etc.
Author-email: "James J. Ramsey" <jjramsey@pobox.com>
License-Expression: GPL-3.0-only
Classifier: Development Status :: 4 - Beta
Classifier: Programming Language :: Python :: 3
Requires-Python: >=3.6
License-File: LICENSE
Requires-Dist: dasbus
Dynamic: license-file
